pygments_better_html/__init__.py
pygments_better_html-0.1.5.dist-info/AUTHORS
pygments_better_html-0.1.5.dist-info/LICENSE
pygments_better_html-0.1.5.dist-info/LICENSE.pygments
pygments_better_html-0.1.5.dist-info/METADATA
pygments_better_html-0.1.5.dist-info/WHEEL
pygments_better_html-0.1.5.dist-info/top_level.txt
pygments_better_html-0.1.5.dist-info/RECORD
