Metadata-Version: 2.1
Name: pygments-better-html
Version: 0.1.5
Summary: Better HTML formatter for Pygments
Home-page: https://github.com/Kwpolska/pygments_better_html
Author: Chris Warrick
Author-email: chris@chriswarrick.com
License: 3-clause BSD
Keywords: pygments,html,code,highlighting
Platform: any
Classifier: Development Status :: 4 - Beta
Classifier: Programming Language :: Python
Classifier: Programming Language :: Python :: 3
Classifier: Topic :: Software Development
License-File: LICENSE
License-File: LICENSE.pygments
License-File: AUTHORS
Requires-Dist: Pygments (>=2.15.1)
